ikcms/__init__.py
ikcms/apps/__init__.py
ikcms/apps/admin/__init__.py
ikcms/apps/admin/app.py
ikcms/apps/admin/cfg.py
ikcms/apps/admin/context.py
ikcms/apps/admin/env.py
ikcms/apps/admin/handler.py
ikcms/apps/admin/menuconf.py
ikcms/apps/admin/models.py
ikcms/apps/admin/preview.py
ikcms/apps/admin/components/__init__.py
ikcms/apps/admin/components/db.py
ikcms/apps/admin/components/render.py
ikcms/apps/admin/static/css/Manifest
ikcms/apps/admin/static/css/preview.css
ikcms/apps/admin/static/js/Manifest
ikcms/apps/admin/static/js/preview.js
ikcms/apps/admin/static/js/lib/jquery-3.2.1.min.js
ikcms/apps/admin/streams/__init__.py
ikcms/apps/admin/streams/admins.py
ikcms/apps/base/__init__.py
ikcms/apps/base/app.py
ikcms/apps/base/cfg.py
ikcms/apps/base/env.py
ikcms/apps/composite/__init__.py
ikcms/apps/composite/app.py
ikcms/apps/composite/cfg.py
ikcms/apps/composite/env.py
ikcms/apps/composite/exc.py
ikcms/apps/web/__init__.py
ikcms/apps/web/app.py
ikcms/apps/web/cfg.py
ikcms/apps/web/handler.py
ikcms/cfg/__init__.py
ikcms/cfg/base.py
ikcms/cli/__init__.py
ikcms/cli/app.py
ikcms/cli/base.py
ikcms/cli/db.py
ikcms/cli/ws_app.py
ikcms/components/__init__.py
ikcms/components/base.py
ikcms/components/cached_tree.py
ikcms/components/app/__init__.py
ikcms/components/cache/__init__.py
ikcms/components/cache/base.py
ikcms/components/cache/dao.py
ikcms/components/cache/mcache.py
ikcms/components/cache/redis.py
ikcms/components/db/__init__.py
ikcms/components/db/base.py
ikcms/components/db/cli.py
ikcms/components/db/sqla.py
ikcms/components/db/generator/__init__.py
ikcms/components/db/generator/generator.py
ikcms/components/db/generator/vesna.py
ikcms/components/i18n/__init__.py
ikcms/components/i18n/catalog.py
ikcms/components/i18n/cli.py
ikcms/components/i18n/handlers.py
ikcms/components/markup/__init__.py
ikcms/components/markup/filters.py
ikcms/components/markup/model.py
ikcms/components/markup/tags.py
ikcms/components/render/__init__.py
ikcms/components/render/base.py
ikcms-0.2.dist-info/METADATA
ikcms-0.2.dist-info/WHEEL
ikcms-0.2.dist-info/entry_points.txt
ikcms-0.2.dist-info/top_level.txt
ikcms-0.2.dist-info/RECORD
